<annotation>
	<folder>VOC2007</folder>
	<filename>000174.jpg</filename>
	<source>
		<database>The VOC2007 Database</database>
		<annotation>PASCAL VOC2007</annotation>
		<image>flickr</image>
		<flickrid>NULL</flickrid>
	</source>
	<owner>
		<flickrid>NULL</flickrid>
		<name>hunterlew</name>
	</owner>
	<size>
		<width>491</width>
		<height>594</height>
		<depth>1</depth>
	</size>
	<segmented>0</segmented>
	<object>
		<name>1</name>
		<pose>Unspecified</pose>
		<truncated>0</truncated>
		<difficult>0</difficult>
		<bndbox>
			<xmin>110</xmin>
			<ymin>466</ymin>
			<xmax>226</xmax>
			<ymax>575</ymax>
		</bndbox>
	</object>
	<object>
		<name>7</name>
		<pose>Unspecified</pose>
		<truncated>0</truncated>
		<difficult>0</difficult>
		<bndbox>
			<xmin>233</xmin>
			<ymin>520</ymin>
			<xmax>330</xmax>
			<ymax>601</ymax>
		</bndbox>
	</object>
</annotation>
