<annotation>
	<folder>VOC2007</folder>
	<filename>000698.jpg</filename>
	<source>
		<database>The VOC2007 Database</database>
		<annotation>PASCAL VOC2007</annotation>
		<image>flickr</image>
		<flickrid>NULL</flickrid>
	</source>
	<owner>
		<flickrid>NULL</flickrid>
		<name>hunterlew</name>
	</owner>
	<size>
		<width>492</width>
		<height>594</height>
		<depth>1</depth>
	</size>
	<segmented>0</segmented>
	<object>
		<name>6</name>
		<pose>Unspecified</pose>
		<truncated>0</truncated>
		<difficult>0</difficult>
		<bndbox>
			<xmin>268</xmin>
			<ymin>193</ymin>
			<xmax>381</xmax>
			<ymax>308</ymax>
		</bndbox>
	</object>
	<object>
		<name>7</name>
		<pose>Unspecified</pose>
		<truncated>0</truncated>
		<difficult>0</difficult>
		<bndbox>
			<xmin>317</xmin>
			<ymin>307</ymin>
			<xmax>434</xmax>
			<ymax>430</ymax>
		</bndbox>
	</object>
</annotation>
